sdbus_async/networkmanager/__init__.py
sdbus_async/networkmanager/enums.py
sdbus_async/networkmanager/exceptions.py
sdbus_async/networkmanager/interfaces_devices.py
sdbus_async/networkmanager/interfaces_other.py
sdbus_async/networkmanager/objects.py
sdbus_async/networkmanager/py.typed
sdbus_async/networkmanager/types.py
sdbus_async/networkmanager/settings/__init__.py
sdbus_async/networkmanager/settings/adsl.py
sdbus_async/networkmanager/settings/base.py
sdbus_async/networkmanager/settings/bluetooth.py
sdbus_async/networkmanager/settings/bond.py
sdbus_async/networkmanager/settings/bond_port.py
sdbus_async/networkmanager/settings/bridge.py
sdbus_async/networkmanager/settings/bridge_port.py
sdbus_async/networkmanager/settings/cdma.py
sdbus_async/networkmanager/settings/connection.py
sdbus_async/networkmanager/settings/datatypes.py
sdbus_async/networkmanager/settings/dcb.py
sdbus_async/networkmanager/settings/dummy.py
sdbus_async/networkmanager/settings/eapol.py
sdbus_async/networkmanager/settings/ethernet.py
sdbus_async/networkmanager/settings/ethtool.py
sdbus_async/networkmanager/settings/generic.py
sdbus_async/networkmanager/settings/gsm.py
sdbus_async/networkmanager/settings/hostname.py
sdbus_async/networkmanager/settings/infiniband.py
sdbus_async/networkmanager/settings/ip_tunnel.py
sdbus_async/networkmanager/settings/ipv4.py
sdbus_async/networkmanager/settings/ipv6.py
sdbus_async/networkmanager/settings/lowpan.py
sdbus_async/networkmanager/settings/macsec.py
sdbus_async/networkmanager/settings/macvlan.py
sdbus_async/networkmanager/settings/match.py
sdbus_async/networkmanager/settings/olpc_mesh.py
sdbus_async/networkmanager/settings/ovs_bridge.py
sdbus_async/networkmanager/settings/ovs_dpdk.py
sdbus_async/networkmanager/settings/ovs_external_ids.py
sdbus_async/networkmanager/settings/ovs_interface.py
sdbus_async/networkmanager/settings/ovs_patch.py
sdbus_async/networkmanager/settings/ovs_port.py
sdbus_async/networkmanager/settings/ppp.py
sdbus_networkmanager-2.0.0.dist-info/COPYING
sdbus_networkmanager-2.0.0.dist-info/COPYING.LESSER
sdbus_networkmanager-2.0.0.dist-info/METADATA
sdbus_networkmanager-2.0.0.dist-info/WHEEL
sdbus_networkmanager-2.0.0.dist-info/top_level.txt
sdbus_networkmanager-2.0.0.dist-info/RECORD
